[{"title": "Boku no Hero Academia 5th Season", "url": "https://myanimelist.net/anime/41587/Boku_no_Hero_Academia_5th_Season", "episodes": "25 eps", "genres": ["Action", "Comedy", "Super Power", "School", "Shounen"], "image": "https://cdn.myanimelist.net/images/anime/1911/113611.jpg"}, {"title": "Ijiranaide, Nagatoro-san", "url": "https://myanimelist.net/anime/42361/Ijiranaide_Nagatoro-san", "episodes": "12 eps", "genres": ["Slice of Life", "Comedy", "Romance"], "image": "https://cdn.myanimelist.net/images/anime/1900/110097.jpg"}, {"title": "Hige wo Soru. Soshite Joshikousei wo Hirou.", "url": "https://myanimelist.net/anime/40938/Hige_wo_Soru_Soshite_Joshikousei_wo_Hirou", "episodes": "13 eps", "genres": ["Drama", "Romance"], "image": "https://cdn.myanimelist.net/images/anime/1146/113477.jpg"}, {"title": "Isekai Maou to Shoukan Shoujo no Dorei Majutsu \u03a9", "url": "https://myanimelist.net/anime/41623/Isekai_Maou_to_Shoukan_Shoujo_no_Dorei_Majutsu_\u03a9", "episodes": "10 eps", "genres": ["Harem", "Comedy", "Magic", "Ecchi", "Fantasy"], "image": "https://cdn.myanimelist.net/images/anime/1011/113703.jpg"}, {"title": "Shaman King (2021)", "url": "https://myanimelist.net/anime/42205/Shaman_King_2021", "episodes": "52 eps", "genres": ["Action", "Adventure", "Comedy", "Super Power", "Supernatural", "Shounen"], "image": "https://cdn.myanimelist.net/images/anime/1416/113270.jpg"}, {"title": "Fumetsu no Anata e", "url": "https://myanimelist.net/anime/41025/Fumetsu_no_Anata_e", "episodes": "20 eps", "genres": ["Adventure", "Supernatural", "Drama", "Shounen"], "image": "https://cdn.myanimelist.net/images/anime/1134/111757.jpg"}, {"title": "Tensura Nikki: Tensei shitara Slime Datta Ken", "url": "https://myanimelist.net/anime/41488/Tensura_Nikki__Tensei_shitara_Slime_Datta_Ken", "episodes": "12 eps", "genres": ["Slice of Life", "Comedy", "Fantasy", "Shounen"], "image": "https://cdn.myanimelist.net/images/anime/1263/112268.jpg"}, {"title": "Fruits Basket: The Final", "url": "https://myanimelist.net/anime/42938/Fruits_Basket__The_Final", "episodes": "No episode estimates", "genres": ["Slice of Life", "Comedy", "Supernatural", "Drama", "Romance", "Shoujo"], "image": "https://cdn.myanimelist.net/images/anime/1803/113269.jpg"}, {"title": "Tokyo Revengers", "url": "https://myanimelist.net/anime/42249/Tokyo_Revengers", "episodes": "No episode estimates", "genres": ["Action", "Drama", "School", "Shounen"], "image": "https://cdn.myanimelist.net/images/anime/1493/113949.jpg"}, {"title": "Zombieland Saga: Revenge", "url": "https://myanimelist.net/anime/40174/Zombieland_Saga__Revenge", "episodes": "12 eps", "genres": ["Music", "Comedy", "Supernatural"], "image": "https://cdn.myanimelist.net/images/anime/1998/110999.jpg"}, {"title": "Sentouin, Hakenshimasu!", "url": "https://myanimelist.net/anime/41456/Sentouin_Hakenshimasu", "episodes": "12 eps", "genres": ["Action", "Comedy", "Fantasy"], "image": "https://cdn.myanimelist.net/images/anime/1262/113705.jpg"}, {"title": "Slime Taoshite 300-nen, Shiranai Uchi ni Level Max ni Nattemashita", "url": "https://myanimelist.net/anime/40586/Slime_Taoshite_300-nen_Shiranai_Uchi_ni_Level_Max_ni_Nattemashita", "episodes": "No episode estimates", "genres": ["Comedy", "Fantasy"], "image": "https://cdn.myanimelist.net/images/anime/1641/113723.jpg"}, {"title": "Edens Zero", "url": "https://myanimelist.net/anime/42192/Edens_Zero", "episodes": "No episode estimates", "genres": ["Action", "Sci-Fi", "Adventure", "Comedy", "Fantasy", "Shounen"], "image": "https://cdn.myanimelist.net/images/anime/1011/111811.jpg"}, {"title": "Nomad: Megalo Box 2", "url": "https://myanimelist.net/anime/40729/Nomad__Megalo_Box_2", "episodes": "13 eps", "genres": ["Action", "Sci-Fi", "Sports", "Drama"], "image": "https://cdn.myanimelist.net/images/anime/1190/113352.jpg"}, {"title": "Koi to Yobu ni wa Kimochi Warui", "url": "https://myanimelist.net/anime/41103/Koi_to_Yobu_ni_wa_Kimochi_Warui", "episodes": "12 eps", "genres": ["Comedy", "Romance"], "image": "https://cdn.myanimelist.net/images/anime/1519/110527.jpg"}, {"title": "Mairimashita! Iruma-kun 2nd Season", "url": "https://myanimelist.net/anime/41402/Mairimashita_Iruma-kun_2nd_Season", "episodes": "21 eps", "genres": ["Comedy", "Demons", "Supernatural", "Fantasy", "School", "Shounen"], "image": "https://cdn.myanimelist.net/images/anime/1527/113656.jpg"}, {"title": "86", "url": "https://myanimelist.net/anime/41457/86", "episodes": "No episode estimates", "genres": ["Action", "Military", "Sci-Fi", "Drama", "Mecha"], "image": "https://cdn.myanimelist.net/images/anime/1104/113797.jpg"}, {"title": "Yuukoku no Moriarty 2nd Season", "url": "https://myanimelist.net/anime/43325/Yuukoku_no_Moriarty_2nd_Season", "episodes": "13 eps", "genres": ["Mystery", "Historical", "Psychological", "Thriller", "Shounen"], "image": "https://cdn.myanimelist.net/images/anime/1200/111522.jpg"}, {"title": "Osananajimi ga Zettai ni Makenai Love Comedy", "url": "https://myanimelist.net/anime/43007/Osananajimi_ga_Zettai_ni_Makenai_Love_Comedy", "episodes": "12 eps", "genres": ["Harem", "Comedy", "Romance", "School"], "image": "https://cdn.myanimelist.net/images/anime/1111/113327.jpg"}, {"title": "Kyuukyoku Shinka shita Full Dive RPG ga Genjitsu yori mo Kusoge Dattara", "url": "https://myanimelist.net/anime/44276/Kyuukyoku_Shinka_shita_Full_Dive_RPG_ga_Genjitsu_yori_mo_Kusoge_Dattara", "episodes": "12 eps", "genres": ["Action", "Game", "Comedy", "Fantasy"], "image": "https://cdn.myanimelist.net/images/anime/1357/113277.jpg"}, {"title": "Vivy: Fluorite Eye's Song", "url": "https://myanimelist.net/anime/46095/Vivy__Fluorite_Eyes_Song", "episodes": "13 eps", "genres": ["Action", "Sci-Fi", "Music", "Thriller"], "image": "https://cdn.myanimelist.net/images/anime/1404/113722.jpg"}, {"title": "SSSS.Dynazenon", "url": "https://myanimelist.net/anime/40870/SSSSDynazenon", "episodes": "12 eps", "genres": ["Action", "Sci-Fi", "Mecha"], "image": "https://cdn.myanimelist.net/images/anime/1880/113766.jpg"}, {"title": "Jouran: The Princess of Snow and Blood", "url": "https://myanimelist.net/anime/47250/Jouran__The_Princess_of_Snow_and_Blood", "episodes": "No episode estimates", "genres": ["Action", "Historical", "Supernatural"], "image": "https://cdn.myanimelist.net/images/anime/1945/113312.jpg"}, {"title": "Shakunetsu Kabaddi", "url": "https://myanimelist.net/anime/42395/Shakunetsu_Kabaddi", "episodes": "12 eps", "genres": ["Sports"], "image": "https://cdn.myanimelist.net/images/anime/1936/114022.jpg"}, {"title": "Seijo no Maryoku wa Bannou Desu", "url": "https://myanimelist.net/anime/42826/Seijo_no_Maryoku_wa_Bannou_Desu", "episodes": "12 eps", "genres": ["Slice of Life", "Magic", "Romance", "Fantasy"], "image": "https://cdn.myanimelist.net/images/anime/1232/111099.jpg"}, {"title": "Mashiro no Oto", "url": "https://myanimelist.net/anime/42590/Mashiro_no_Oto", "episodes": "12 eps", "genres": ["Music", "Slice of Life", "Drama", "School", "Shounen"], "image": "https://cdn.myanimelist.net/images/anime/1841/111554.jpg"}, {"title": "Subarashiki Kono Sekai The Animation", "url": "https://myanimelist.net/anime/42307/Subarashiki_Kono_Sekai_The_Animation", "episodes": "12 eps", "genres": ["Action", "Adventure"], "image": "https://cdn.myanimelist.net/images/anime/1016/111566.jpg"}, {"title": "Shadows House", "url": "https://myanimelist.net/anime/43439/Shadows_House", "episodes": "No episode estimates", "genres": ["Slice of Life", "Supernatural", "Seinen"], "image": "https://cdn.myanimelist.net/images/anime/1424/113342.jpg"}, {"title": "Super Cub", "url": "https://myanimelist.net/anime/40685/Super_Cub", "episodes": "No episode estimates", "genres": ["Slice of Life", "School"], "image": "https://cdn.myanimelist.net/images/anime/1776/111172.jpg"}, {"title": "Godzilla: S.P", "url": "https://myanimelist.net/anime/43229/Godzilla__SP", "episodes": "13 eps", "genres": ["Action", "Sci-Fi", "Mecha"], "image": "https://cdn.myanimelist.net/images/anime/1828/112581.jpg"}, {"title": "Bakuten!!", "url": "https://myanimelist.net/anime/43756/Bakuten", "episodes": "12 eps", "genres": ["Sports"], "image": "https://cdn.myanimelist.net/images/anime/1827/113510.jpg"}, {"title": "Sayonara Watashi no Cramer", "url": "https://myanimelist.net/anime/42774/Sayonara_Watashi_no_Cramer", "episodes": "13 eps", "genres": ["Sports", "Drama", "Shounen"], "image": "https://cdn.myanimelist.net/images/anime/1155/111437.jpg"}, {"title": "Dragon, Ie wo Kau.", "url": "https://myanimelist.net/anime/40526/Dragon_Ie_wo_Kau", "episodes": "12 eps", "genres": ["Comedy", "Fantasy", "Shounen"], "image": "https://cdn.myanimelist.net/images/anime/1876/114021.jpg"}, {"title": "Yakunara Mug Cup mo", "url": "https://myanimelist.net/anime/42568/Yakunara_Mug_Cup_mo", "episodes": "12 eps", "genres": ["Slice of Life"], "image": "https://cdn.myanimelist.net/images/anime/1969/113673.jpg"}, {"title": "Odd Taxi", "url": "https://myanimelist.net/anime/46102/Odd_Taxi", "episodes": "No episode estimates", "genres": ["Mystery"], "image": "https://cdn.myanimelist.net/images/anime/1981/113348.jpg"}, {"title": "Bishounen Tanteidan", "url": "https://myanimelist.net/anime/40752/Bishounen_Tanteidan", "episodes": "No episode estimates", "genres": ["Mystery", "School"], "image": "https://cdn.myanimelist.net/images/anime/1925/110172.jpg"}, {"title": "Seven Knights Revolution: Eiyuu no Keishousha", "url": "https://myanimelist.net/anime/47391/Seven_Knights_Revolution__Eiyuu_no_Keishousha", "episodes": "No episode estimates", "genres": ["Action", "Adventure", "Magic", "Fantasy"], "image": "https://cdn.myanimelist.net/images/anime/1079/114017.jpg"}, {"title": "Blue Reflection Ray", "url": "https://myanimelist.net/anime/47639/Blue_Reflection_Ray", "episodes": "24 eps", "genres": ["Magic", "School"], "image": "https://cdn.myanimelist.net/images/anime/1496/113840.jpg"}, {"title": "Cestvs: The Roman Fighter", "url": "https://myanimelist.net/anime/43763/Cestvs__The_Roman_Fighter", "episodes": "No episode estimates", "genres": ["Action", "Historical", "Drama", "Seinen"], "image": "https://cdn.myanimelist.net/images/anime/1291/114014.jpg"}, {"title": "Fairy Ranmaru: Anata no Kokoro Otasuke Shimasu", "url": "https://myanimelist.net/anime/45665/Fairy_Ranmaru__Anata_no_Kokoro_Otasuke_Shimasu", "episodes": "12 eps", "genres": ["Action", "Slice of Life", "Magic", "School"], "image": "https://cdn.myanimelist.net/images/anime/1476/114026.jpg"}, {"title": "Cardfight!! Vanguard: overDress", "url": "https://myanimelist.net/anime/42516/Cardfight_Vanguard__overDress", "episodes": "12 eps", "genres": ["Action", "Game"], "image": "https://cdn.myanimelist.net/images/anime/1520/113748.jpg"}, {"title": "Yuuki Yuuna wa Yuusha de Aru Churutto!", "url": "https://myanimelist.net/anime/42071/Yuuki_Yuuna_wa_Yuusha_de_Aru_Churutto", "episodes": "No episode estimates", "genres": ["Slice of Life", "Comedy", "Drama", "Magic", "Fantasy"], "image": "https://cdn.myanimelist.net/images/anime/1827/107735.jpg"}, {"title": "Battle Athletess Daiundoukai ReSTART!", "url": "https://myanimelist.net/anime/42321/Battle_Athletess_Daiundoukai_ReSTART", "episodes": "No episode estimates", "genres": ["Action", "Sci-Fi", "Adventure", "Comedy", "Sports", "School"], "image": "https://cdn.myanimelist.net/images/anime/1752/113795.jpg"}, {"title": "Dinosaur Biyori", "url": "https://myanimelist.net/anime/45618/Dinosaur_Biyori", "episodes": "26 eps", "genres": ["Slice of Life"], "image": "https://cdn.myanimelist.net/images/anime/1857/111015.jpg"}, {"title": "Itazuraguma no Gloomy", "url": "https://myanimelist.net/anime/45587/Itazuraguma_no_Gloomy", "episodes": "No episode estimates", "genres": ["Comedy"], "image": "https://cdn.myanimelist.net/images/anime/1289/113575.jpg"}, {"title": "Shikaru Neko", "url": "https://myanimelist.net/anime/48442/Shikaru_Neko", "episodes": "No episode estimates", "genres": ["Slice of Life"], "image": "https://cdn.myanimelist.net/images/anime/1008/113384.jpg"}, {"title": "Mazica Party", "url": "https://myanimelist.net/anime/48391/Mazica_Party", "episodes": "No episode estimates", "genres": ["Game", "Magic", "Fantasy"], "image": "https://cdn.myanimelist.net/images/anime/1740/113501.jpg"}, {"title": "Duel Masters King!", "url": "https://myanimelist.net/anime/46652/Duel_Masters_King", "episodes": "No episode estimates", "genres": ["Action", "Adventure", "Comedy", "Shounen"], "image": "https://cdn.myanimelist.net/images/anime/1159/111981.jpg"}, {"title": "Uchuu Nanchara Kotetsu-kun", "url": "https://myanimelist.net/anime/42870/Uchuu_Nanchara_Kotetsu-kun", "episodes": "No episode estimates", "genres": ["Space", "Comedy"], "image": "https://cdn.myanimelist.net/images/anime/1345/113576.jpg"}, {"title": "Utau Soccer Panda Mifanda", "url": "https://myanimelist.net/anime/42068/Utau_Soccer_Panda_Mifanda", "episodes": "No episode estimates", "genres": ["Music", "Slice of Life"], "image": "https://cdn.myanimelist.net/images/anime/1296/108533.jpg"}]